bindings_cpp.cpython-310-i386-linux-gnu.so
tests/test_proj_utils.py
tests/test_image.py
tests/helpers.py
tests/test_dtm_image.py
tests/conftest.py
tests/__init__.py
tests/geofunctions/test_triangulation.py
tests/geofunctions/test_localization_optim.py
tests/geofunctions/test_rectification.py
tests/geofunctions/test_rectification_optim.py
tests/geofunctions/test_localization.py
tests/geofunctions/test_strip_rectification_grid.py
tests/geofunctions/test_dtm_intersection.py
tests/geofunctions/test_dtm_intersection_optim.py
tests/geofunctions/__init__.py
tests/geomodels/test_rpc.py
tests/geomodels/test_los.py
tests/geomodels/test_grid.py
tests/geomodels/__init__.py
tests/geomodels/test_rpc_optim.py
shareloc-0.2.10.dist-info/WHEEL
shareloc-0.2.10.dist-info/entry_points.txt
shareloc-0.2.10.dist-info/top_level.txt
shareloc-0.2.10.dist-info/METADATA
shareloc-0.2.10.dist-info/RECORD
shareloc-0.2.10.dist-info/licenses/LICENSE
shareloc/dtm_reader.py
shareloc/math_utils.py
shareloc/proj_utils.py
shareloc/rpc_converter.py
shareloc/image.py
shareloc/__init__.py
shareloc/geofunctions/localization.py
shareloc/geofunctions/rectification_grid.py
shareloc/geofunctions/triangulation.py
shareloc/geofunctions/dtm_intersection.py
shareloc/geofunctions/__init__.py
shareloc/geofunctions/rectification.py
shareloc/geomodels/los.py
shareloc/geomodels/rpc_optim.py
shareloc/geomodels/geomodel.py
shareloc/geomodels/rpc_readers.py
shareloc/geomodels/rpc.py
shareloc/geomodels/grid.py
shareloc/geomodels/geomodel_template.py
shareloc/geomodels/rpc_writers.py
shareloc/geomodels/__init__.py
