Metadata-Version: 2.4
Name: shareloc
Version: 0.2.10
Summary: Simple geometry library
Home-page: https://shareloc.readthedocs.io/
Author: CNES
Author-email: cars@cnes.fr
License: Apache License 2.0
Project-URL: Source, https://github.com/CNES/shareloc
Project-URL: Documentation, https://shareloc.readthedocs.io/en/latest/
Keywords: shareloc,cars,3D,DEM,pandora,photogrammetry
Platform: any
Classifier: Development Status :: 4 - Beta
Classifier: Intended Audience :: Developers
Classifier: Intended Audience :: End Users/Desktop
Classifier: Intended Audience :: Science/Research
Classifier: Environment :: Console
Classifier: Topic :: Software Development :: Libraries :: Python Modules
Classifier: License :: OSI Approved :: Apache Software License
Classifier: Operating System :: OS Independent
Classifier: Programming Language :: Python
Classifier: Programming Language :: Python :: 3.9
Requires-Python: >=3.9
License-File: LICENSE
Requires-Dist: numpy>=1.17.0
Requires-Dist: scipy!=1.10.0,>=1.7.1
Requires-Dist: rasterio
Requires-Dist: xarray
Requires-Dist: numba
Requires-Dist: pybind11
Requires-Dist: pyarrow
Provides-Extra: dev
Requires-Dist: pre-commit; extra == "dev"
Requires-Dist: isort>=5.8.0; extra == "dev"
Requires-Dist: black>=21.5b0; extra == "dev"
Requires-Dist: flake8>=3.9.1; extra == "dev"
Requires-Dist: flake8-comprehensions>=3.4.0; extra == "dev"
Requires-Dist: flake8-bugbear>=21.4.3; extra == "dev"
Requires-Dist: pylint>=2.8.2; extra == "dev"
Requires-Dist: setuptools_scm; extra == "dev"
Requires-Dist: virtualenv; extra == "dev"
Requires-Dist: configupdater; extra == "dev"
Requires-Dist: twine; extra == "dev"
Requires-Dist: build; extra == "dev"
Requires-Dist: pytest; extra == "dev"
Requires-Dist: pytest-cov; extra == "dev"
Requires-Dist: pytest-sugar; extra == "dev"
Requires-Dist: tox; extra == "dev"
Requires-Dist: mypy; extra == "dev"
Requires-Dist: pybind11; extra == "dev"
Provides-Extra: docs
Requires-Dist: sphinx; extra == "docs"
Requires-Dist: sphinx-rtd-theme; extra == "docs"
Requires-Dist: graphviz; extra == "docs"
Requires-Dist: sphinx_autoapi; extra == "docs"
Requires-Dist: sphinx_tabs; extra == "docs"
Provides-Extra: notebook
Requires-Dist: notebook; extra == "notebook"
Requires-Dist: bokeh; extra == "notebook"
Dynamic: license-file
